flask_meld/__init__.py
flask_meld/cli.py
flask_meld/component.py
flask_meld/meld.py
flask_meld/message.py
flask_meld/tag.py
flask_meld/templates.py
flask_meld/meld_js_src/attribute.js
flask_meld/meld_js_src/component.js
flask_meld/meld_js_src/element.js
flask_meld/meld_js_src/meld.js
flask_meld/meld_js_src/morphdom-umd.js
flask_meld/meld_js_src/socket.io.js
flask_meld/meld_js_src/socket.io.min.js.map
flask_meld/meld_js_src/utils.js
Flask_Meld-0.13.1.dist-info/LICENSE
Flask_Meld-0.13.1.dist-info/METADATA
Flask_Meld-0.13.1.dist-info/WHEEL
Flask_Meld-0.13.1.dist-info/entry_points.txt
Flask_Meld-0.13.1.dist-info/top_level.txt
Flask_Meld-0.13.1.dist-info/RECORD
