Metadata-Version: 2.1
Name: Flask-Meld
Version: 0.13.1
Summary: Meld is a framework for Flask that allows you to create dynamic user interfaces using Python and the Jinja2 templating engine.
Home-page: http://github.com/mikeabrahamsen/Flask-Meld/
Author: Michael Abrahamsen
Author-email: mail@michaelabrahamsen.com
License: MIT
Platform: any
Classifier: Environment :: Web Environment
Classifier: Intended Audience :: Developers
Classifier: License :: OSI Approved :: MIT License
Classifier: Operating System :: OS Independent
Classifier: Programming Language :: Python
Classifier: Programming Language :: Python :: 3
Classifier: Topic :: Internet :: WWW/HTTP :: Dynamic Content
Classifier: Topic :: Software Development :: Libraries :: Python Modules
License-File: LICENSE
Requires-Dist: Flask (>=0.9)
Requires-Dist: beautifulsoup4 (>=4)
Requires-Dist: orjson (>=3.4.6)
Requires-Dist: flask-socketio (>=5)
Requires-Dist: gevent-websocket (>=0.10.1)
Requires-Dist: jinja2-simple-tags (==0.3.1)
Requires-Dist: click (==7.1.2)
